MANIFEST.in
README
setup.py
catalog/__init__.py
catalog/admin.py
catalog/base.py
catalog/direct.py
catalog/dummy_mptt.py
catalog/forms.py
catalog/grid_to_json.py
catalog/models.py
catalog/settings.py
catalog/tests.py
catalog/utils.py
catalog/views.py
catalog/contrib/__init__.py
catalog/contrib/defaults/__init__.py
catalog/contrib/defaults/admin.py
catalog/contrib/defaults/ikspecs.py
catalog/contrib/defaults/models.py
catalog/contrib/defaults/settings.py
catalog/contrib/defaults/urls.py
catalog/contrib/defaults/management/__init__.py
catalog/contrib/defaults/management/commands/__init__.py
catalog/contrib/defaults/management/commands/importcsv.py
catalog/contrib/defaults/management/commands/importmedia.py
catalog/contrib/defaults/management/commands/makeprice.py
catalog/media/catalog/img/cog_edit.png
catalog/media/catalog/img/delete.png
catalog/media/catalog/js/catalog.js
catalog/redsolution_setup/__init__.py
catalog/redsolution_setup/make.py
catalog/redsolution_setup/templates/catalog/redsolutioncms/settings.pyt
catalog/static/catalog/img/cog_edit.png
catalog/static/catalog/img/delete.png
catalog/static/catalog/js/catalog.js
catalog/templates/admin/catalog/change_form_with_links.html
catalog/templates/admin/catalog/change_treeiem.html
catalog/templates/admin/catalog/closepopup.html
catalog/templates/admin/catalog/extjs_admin.html
catalog/templates/admin/catalog/link_add_form.html
catalog/templates/admin/catalog/move_node_form.html
catalog/templates/catalog/base.html
catalog/templates/catalog/breadcrumbs.html
catalog/templates/catalog/children_tag.html
catalog/templates/catalog/root.html
catalog/templates/catalog/tree.html
catalog/templates/catalog/treeitem.html
catalog/templatetags/__init__.py
catalog/templatetags/catalog_admin.py
catalog/templatetags/catalog_tags.py
catalog/tests/__init__.py
catalog/tests/catalog_testmaker.py
catalog/urls/__init__.py
catalog/urls/by_id.py
catalog/urls/by_slug.py
django_catalog.egg-info/PKG-INFO
django_catalog.egg-info/SOURCES.txt
django_catalog.egg-info/dependency_links.txt
django_catalog.egg-info/entry_points.txt
django_catalog.egg-info/not-zip-safe
django_catalog.egg-info/requires.txt
django_catalog.egg-info/top_level.txt